README.rst
setup.py
master_password/__init__.py
master_password/__main__.py
master_password/_get_scrypt.py
master_password/datatypes.py
master_password/ddd.py
master_password/helpers.py
master_password/mpsites.py
master_password/tests.py
master_password.egg-info/PKG-INFO
master_password.egg-info/SOURCES.txt
master_password.egg-info/dependency_links.txt
master_password.egg-info/entry_points.txt
master_password.egg-info/requires.txt
master_password.egg-info/top_level.txt