Metadata-Version: 1.1
Name: master-password
Version: 1.3.0
Summary: An implementation of the Master Password© algorithm in Python
Home-page: https://github.com/MitalAshok/master_password
Author: Mital Ashok
Author-email: mital.vaja@googlemail.com
License: GPL-3.0
Keywords: masterpassword,statelesspassword,password
Platform: UNKNOWN
Classifier: Development Status :: 5 - Production/Stable
Classifier: Topic :: Security
Classifier: License :: OSI Approved :: GNU General Public License v3 (GPLv3)
Classifier: Programming Language :: Python :: 2
Classifier: Programming Language :: Python :: 2.6
Classifier: Programming Language :: Python :: 2.7
Classifier: Programming Language :: Python :: 3
Classifier: Programming Language :: Python :: 3.3
Classifier: Programming Language :: Python :: 3.4
Classifier: Programming Language :: Python :: 3.5
